git_project_status/__init__.py
git_project_status/__main__.py
git_project_status/py.typed
git_project_status-0.0.13.dist-info/entry_points.txt
git_project_status-0.0.13.dist-info/LICENSE
git_project_status-0.0.13.dist-info/WHEEL
git_project_status-0.0.13.dist-info/METADATA
git_project_status-0.0.13.dist-info/RECORD
