Metadata-Version: 2.1
Name: git-project-status
Version: 0.0.13
Summary: Check subdirectories for dirty repos.
License: MIT
Keywords: git
Author: James Hodgkinson
Author-email: james@terminaloutcomes.com
Requires-Python: >=3.8,<4.0
Classifier: Development Status :: 5 - Production/Stable
Classifier: Intended Audience :: Developers
Classifier: License :: OSI Approved :: MIT License
Classifier: Programming Language :: Python :: 3
Classifier: Programming Language :: Python :: 3.10
Classifier: Programming Language :: Python :: 3.8
Classifier: Programming Language :: Python :: 3.9
Classifier: Topic :: Internet :: WWW/HTTP :: Dynamic Content
Requires-Dist: GitPython (>=3.1.27,<4.0.0)
Requires-Dist: click (>=8.1.3,<9.0.0)
Requires-Dist: loguru (>=0.6.0,<0.7.0)
